interactive_buttons/__init__.py
interactive_buttons/ib_exceptions.py
interactive_buttons-3.5.0.dist-info/METADATA
interactive_buttons-3.5.0.dist-info/WHEEL
interactive_buttons-3.5.0.dist-info/top_level.txt
interactive_buttons-3.5.0.dist-info/RECORD
