Metadata-Version: 2.1
Name: interactive-buttons
Version: 3.5.0
Author: Mathys B
Author-email: mathys.boyer@pro.mbinc.tech
Requires-Dist: keyboard
Requires-Dist: pynput ==1.7.6
